{
  "history": [
    {
      "date": "2025-08-03",
      "percentages": {
        "total": {
          "usd": 18.42,
          "eur": 13.92
        },
        "excl_sgov": {
          "usd": 45.44,
          "eur": 38.33
        },
        "btc": {
          "usd": 92.89,
          "eur": 79.88
        },
        "voo": {
          "usd": 13.01,
          "eur": 7.7
        },
        "iau": {
          "usd": 8.34,
          "eur": 4.61
        },
        "nanc": {
          "usd": 7.05,
          "eur": 4.85
        },
        "sgov": {
          "usd": 0.72,
          "eur": -2.37
        }
      }
    },
    {
      "date": "2025-08-02",
      "percentages": {
        "total": {
          "usd": 18.39,
          "eur": 13.98
        },
        "excl_sgov": {
          "usd": 45.73,
          "eur": 38.71
        },
        "btc": {
          "usd": 93.58,
          "eur": 80.64
        },
        "voo": {
          "usd": 13.01,
          "eur": 7.77
        },
        "iau": {
          "usd": 8.34,
          "eur": 4.68
        },
        "nanc": {
          "usd": 7.05,
          "eur": 4.93
        },
        "sgov": {
          "usd": 0.49,
          "eur": -2.53
        }
      }
    },
    {
      "date": "2025-08-01",
      "percentages": {
        "total": {
          "usd": 19.1,
          "eur": 16.23
        },
        "excl_sgov": {
          "usd": 47.02,
          "eur": 41.85
        },
        "btc": {
          "usd": 96.59,
          "eur": 85.96
        },
        "voo": {
          "usd": 14.9,
          "eur": 11.08
        },
        "iau": {
          "usd": 6.15,
          "eur": 3.97
        },
        "nanc": {
          "usd": 8.86,
          "eur": 8.15
        },
        "sgov": {
          "usd": 0.82,
          "eur": -0.87
        }
      }
    },
    {
      "date": "2025-07-31",
      "percentages": {
        "total": {
          "usd": 19.88,
          "eur": 16.92
        },
        "excl_sgov": {
          "usd": 49.0,
          "eur": 43.68
        },
        "btc": {
          "usd": 101.31,
          "eur": 90.32
        },
        "voo": {
          "usd": 15.34,
          "eur": 11.43
        },
        "iau": {
          "usd": 5.48,
          "eur": 3.26
        },
        "nanc": {
          "usd": 9.16,
          "eur": 8.4
        },
        "sgov": {
          "usd": 0.81,
          "eur": -0.93
        }
      }
    },
    {
      "date": "2025-07-30",
      "percentages": {
        "total": {
          "usd": 20.01,
          "eur": 15.71
        },
        "excl_sgov": {
          "usd": 49.36,
          "eur": 42.38
        },
        "btc": {
          "usd": 100.93,
          "eur": 87.8
        },
        "voo": {
          "usd": 15.48,
          "eur": 10.3
        },
        "iau": {
          "usd": 7.31,
          "eur": 3.85
        },
        "nanc": {
          "usd": 9.29,
          "eur": 7.29
        },
        "sgov": {
          "usd": 0.79,
          "eur": -2.08
        }
      }
    },
    {
      "date": "2025-07-29",
      "percentages": {
        "total": {
          "usd": 20.02,
          "eur": 15.44
        },
        "excl_sgov": {
          "usd": 49.39,
          "eur": 42.06
        },
        "btc": {
          "usd": 100.96,
          "eur": 87.36
        },
        "voo": {
          "usd": 15.78,
          "eur": 10.31
        },
        "iau": {
          "usd": 7.02,
          "eur": 3.32
        },
        "nanc": {
          "usd": 9.62,
          "eur": 7.35
        },
        "sgov": {
          "usd": 0.79,
          "eur": -2.32
        }
      }
    },
    {
      "date": "2025-07-28",
      "percentages": {
        "total": {
          "usd": 20.4,
          "eur": 14.15
        },
        "excl_sgov": {
          "usd": 50.4,
          "eur": 40.97
        },
        "btc": {
          "usd": 102.86,
          "eur": 86.42
        },
        "voo": {
          "usd": 15.81,
          "eur": 8.76
        },
        "iau": {
          "usd": 7.69,
          "eur": 2.47
        },
        "nanc": {
          "usd": 9.65,
          "eur": 5.84
        },
        "sgov": {
          "usd": 0.76,
          "eur": -3.75
        }
      }
    },
    {
      "date": "2025-07-27",
      "percentages": {
        "total": {
          "usd": 20.14,
          "eur": 14.04
        },
        "excl_sgov": {
          "usd": 49.73,
          "eur": 40.52
        },
        "btc": {
          "usd": 101.33,
          "eur": 85.24
        },
        "voo": {
          "usd": 15.81,
          "eur": 8.89
        },
        "iau": {
          "usd": 7.69,
          "eur": 2.6
        },
        "nanc": {
          "usd": 9.65,
          "eur": 5.97
        },
        "sgov": {
          "usd": 0.76,
          "eur": -3.63
        }
      }
    },
    {
      "date": "2025-07-26",
      "percentages": {
        "total": {
          "usd": 19.91,
          "eur": 13.81
        },
        "excl_sgov": {
          "usd": 49.15,
          "eur": 39.96
        },
        "btc": {
          "usd": 99.99,
          "eur": 84.0
        },
        "voo": {
          "usd": 15.81,
          "eur": 8.88
        },
        "iau": {
          "usd": 7.69,
          "eur": 2.59
        },
        "nanc": {
          "usd": 9.65,
          "eur": 5.96
        },
        "sgov": {
          "usd": 0.76,
          "eur": -3.64
        }
      }
    },
    {
      "date": "2025-07-25",
      "percentages": {
        "total": {
          "usd": 19.54,
          "eur": 13.63
        },
        "excl_sgov": {
          "usd": 48.21,
          "eur": 39.29
        },
        "btc": {
          "usd": 98.03,
          "eur": 82.47
        },
        "voo": {
          "usd": 15.77,
          "eur": 9.01
        },
        "iau": {
          "usd": 7.44,
          "eur": 2.51
        },
        "nanc": {
          "usd": 9.52,
          "eur": 5.99
        },
        "sgov": {
          "usd": 0.77,
          "eur": -3.49
        }
      }
    },
    {
      "date": "2025-07-24",
      "percentages": {
        "total": {
          "usd": 20.5,
          "eur": 14.2
        },
        "excl_sgov": {
          "usd": 50.68,
          "eur": 41.19
        },
        "btc": {
          "usd": 102.94,
          "eur": 86.44
        },
        "voo": {
          "usd": 15.27,
          "eur": 8.22
        },
        "iau": {
          "usd": 9.4,
          "eur": 4.07
        },
        "nanc": {
          "usd": 8.85,
          "eur": 5.03
        },
        "sgov": {
          "usd": 0.73,
          "eur": -3.81
        }
      }
    },
    {
      "date": "2025-07-23",
      "percentages": {
        "total": {
          "usd": 20.47,
          "eur": 14.18
        },
        "excl_sgov": {
          "usd": 50.62,
          "eur": 41.13
        },
        "btc": {
          "usd": 102.8,
          "eur": 86.31
        },
        "voo": {
          "usd": 15.27,
          "eur": 8.22
        },
        "iau": {
          "usd": 9.4,
          "eur": 4.07
        },
        "nanc": {
          "usd": 8.85,
          "eur": 5.03
        },
        "sgov": {
          "usd": 0.73,
          "eur": -3.81
        }
      }
    }
  ]
}